vzool_config/__init__.py
vzool_config/config_manager.py
vzool_config-0.0.1.dist-info/LICENSE
vzool_config-0.0.1.dist-info/METADATA
vzool_config-0.0.1.dist-info/WHEEL
vzool_config-0.0.1.dist-info/top_level.txt
vzool_config-0.0.1.dist-info/RECORD
