Metadata-Version: 2.1
Name: vzool-config
Version: 0.0.1
Summary: A class for managing configuration settings in a SQLite database.
Author: Abdelaziz Elrashed Elshaikh Mohamed
Author-email: Abdelaziz Elrashed Elshaikh Mohamed <aeemh.sdn@gmail.com>
Project-URL: Homepage, https://github.com/vzool/vzool-config.py
Project-URL: Issues, https://github.com/vzool/vzool-config.py/issues
Classifier: Development Status :: 2 - Pre-Alpha
Classifier: Intended Audience :: Developers
Classifier: Programming Language :: Python :: 3
Classifier: Programming Language :: Python :: 3.9
Classifier: Programming Language :: Python :: 3.10
Classifier: Programming Language :: Python :: 3.11
Classifier: Programming Language :: Python :: 3.12
Classifier: License :: OSI Approved :: MIT License
Classifier: Operating System :: OS Independent
Requires-Python: >=3.9
License-File: LICENSE
